setup.py
oceanlib/__init__.py
oceanlib.egg-info/PKG-INFO
oceanlib.egg-info/SOURCES.txt
oceanlib.egg-info/dependency_links.txt
oceanlib.egg-info/not-zip-safe
oceanlib.egg-info/top_level.txt
oceanlib/fishes/__init__.py
oceanlib/fishes/backtest.py
oceanlib/fishes/portfolio.py
oceanlib/fishes/trade.py
oceanlib/util/__init__.py
oceanlib/util/breeze.py
oceanlib/util/minerals.py
oceanlib/util/water.py